pytest_logdog/__init__.py
pytest_logdog/plugin.py
pytest_logdog-0.1.0.dist-info/LICENSE
pytest_logdog-0.1.0.dist-info/METADATA
pytest_logdog-0.1.0.dist-info/WHEEL
pytest_logdog-0.1.0.dist-info/entry_points.txt
pytest_logdog-0.1.0.dist-info/top_level.txt
pytest_logdog-0.1.0.dist-info/RECORD
