Metadata-Version: 2.1
Name: pytest-logdog
Version: 0.1.0
Summary: Pytest plugin to test logging
Home-page: https://github.com/ods/pytest-logdog
Author: Denis Otkidach
Author-email: denis.otkidach@gmail.com
License: MIT
Platform: UNKNOWN
Classifier: Development Status :: 1 - Planning
Classifier: Intended Audience :: Developers
Classifier: License :: OSI Approved :: MIT License
Classifier: Programming Language :: Python :: 3.7
Classifier: Programming Language :: Python :: 3.8
Classifier: Programming Language :: Python :: 3.9
Classifier: Topic :: Software Development :: Testing
Classifier: Framework :: Pytest
Requires-Python: >=3.7
Requires-Dist: pytest (>=6.2.0)
